<annotation>
	<folder>label</folder>
	<filename>cucumber_0_5007 (9).jpg</filename>
	<path>F:/data-111/label/cucumber_0_5007 (9).jpg</path>
	<source>
		<database>Unknown</database>
	</source>
	<size>
		<width>1059</width>
		<height>812</height>
		<depth>1</depth>
	</size>
	<segmented>0</segmented>
	<object>
		<name>Dune</name>
		<pose>Unspecified</pose>
		<truncated>0</truncated>
		<difficult>0</difficult>
		<bndbox>
			<xmin>327</xmin>
			<ymin>320</ymin>
			<xmax>474</xmax>
			<ymax>456</ymax>
		</bndbox>
	</object>
	<object>
		<name>Dune</name>
		<pose>Unspecified</pose>
		<truncated>0</truncated>
		<difficult>0</difficult>
		<bndbox>
			<xmin>404</xmin>
			<ymin>174</ymin>
			<xmax>539</xmax>
			<ymax>358</ymax>
		</bndbox>
	</object>
	<object>
		<name>Dune</name>
		<pose>Unspecified</pose>
		<truncated>0</truncated>
		<difficult>0</difficult>
		<bndbox>
			<xmin>501</xmin>
			<ymin>84</ymin>
			<xmax>628</xmax>
			<ymax>322</ymax>
		</bndbox>
	</object>
	<object>
		<name>Dune</name>
		<pose>Unspecified</pose>
		<truncated>0</truncated>
		<difficult>0</difficult>
		<bndbox>
			<xmin>452</xmin>
			<ymin>450</ymin>
			<xmax>588</xmax>
			<ymax>561</ymax>
		</bndbox>
	</object>
	<object>
		<name>Submerged dike</name>
		<pose>Unspecified</pose>
		<truncated>0</truncated>
		<difficult>0</difficult>
		<bndbox>
			<xmin>76</xmin>
			<ymin>685</ymin>
			<xmax>331</xmax>
			<ymax>808</ymax>
		</bndbox>
	</object>
	<object>
		<name>Scarp</name>
		<pose>Unspecified</pose>
		<truncated>0</truncated>
		<difficult>0</difficult>
		<bndbox>
			<xmin>619</xmin>
			<ymin>459</ymin>
			<xmax>771</xmax>
			<ymax>749</ymax>
		</bndbox>
	</object>
	<object>
		<name>Scarp</name>
		<pose>Unspecified</pose>
		<truncated>0</truncated>
		<difficult>0</difficult>
		<bndbox>
			<xmin>316</xmin>
			<ymin>722</ymin>
			<xmax>437</xmax>
			<ymax>806</ymax>
		</bndbox>
	</object>
</annotation>
